LICENSE.txt
README.md
setup.cfg
setup.py
pycalib/__init__.py
pycalib/metrics.py
pycalib/stats.py
pycalib/utils.py
pycalib.egg-info/PKG-INFO
pycalib.egg-info/SOURCES.txt
pycalib.egg-info/dependency_links.txt
pycalib.egg-info/requires.txt
pycalib.egg-info/top_level.txt
pycalib/models/__init__.py
pycalib/models/calibrators.py
pycalib/models/multiclass.py
pycalib/tests/__init__.py
pycalib/tests/test_metrics.py
pycalib/tests/models/__init__.py
pycalib/tests/models/test_init.py
pycalib/visualisations/__init__.py
pycalib/visualisations/barycentric.py
pycalib/visualisations/plot.py
pycalib/visualisations/ternary.py
pycalib/visualisations/tests/__init__.py
pycalib/visualisations/tests/test_init.py