Metadata-Version: 2.1
Name: pycalib
Version: 0.1.0.dev6
Summary: Python library with tools for classifier calibration.
Home-page: https://classifier-calibration.github.io/PyCalib/
Download-URL: https://github.com/classifier-calibration/archive/0.1.0.dev6.tar.gz
Author: Miquel Perello Nieto, Hao Song, Telmo de Menezes e Silva Filho
Author-email: perello.nieto@gmail.com
Keywords: classifier calibration,calibration,classification
License-File: LICENSE.txt
Requires-Dist: numpy>=1.22
Requires-Dist: scipy>=1.6
Requires-Dist: scikit-learn>=0.24
Requires-Dist: matplotlib>=3.3
Requires-Dist: statsmodels>=0.12
